{
  "themes": [
    {
      "id": 1,
      "name": "Urban",
      "contacts": [
        "Noel Hendricks"
      ],
      "children": []
    },
    {
      "id": 2,
      "name": "Enclosed Farmland",
      "contacts": [
        "Diogo Francis",
        "Beatrice Travis"
      ],
      "children": []
    },
    {
      "id": 3,
      "name": "Freshwater",
      "contacts": [
        "Seren Mckee",
        "Tyra Cross"
      ],
      "children": [
        {
          "id": 4,
          "name": "Fisheries",
          "contacts": [],
          "children": [],
          "parent": "[CIRCULAR]"
        }
      ]
    },
    {
      "id": 5,
      "name": "Healthy Places",
      "contacts": [],
      "children": [
        {
          "id":6,
          "name": "People & the Environment",
          "contacts": [],
          "children": [],
          "parent": "[CIRCULAR]"
        },
        {
          "id":7,
          "name": "Health Recreation & Wellbeing",
          "contacts": [
            "Brendon Robinson",
            "Katya Barr",
            "Ann-Marie Hodge"
          ],
          "children": [],
          "parent": "[CIRCULAR]"
        },
        {
          "id": 8,
          "name": "Attitudes & Behaviours",
          "contacts": [],
          "children": [],
          "parent": "[CIRCULAR]"
        },
        {
          "id": 9,
          "name": "Geodiversity",
          "contacts": [
            "Zara Macfarlane"
          ],
          "children": [],
          "parent": "[CIRCULAR]"
        }
      ]
    }
  ]
}
